busline/__init__.py
busline/exceptions.py
busline/client/__init__.py
busline/client/eventbus_connector.py
busline/client/pubsub_client.py
busline/client/publisher/__init__.py
busline/client/publisher/publisher.py
busline/client/subscriber/__init__.py
busline/client/subscriber/subscriber.py
busline/client/subscriber/event_handler/__init__.py
busline/client/subscriber/event_handler/callback_event_handler.py
busline/client/subscriber/event_handler/event_handler.py
busline/client/subscriber/event_handler/multi_handler.py
busline/event/__init__.py
busline/event/event.py
busline/event/registry.py
busline/event/message/__init__.py
busline/event/message/avro_message.py
busline/event/message/json_message.py
busline/event/message/message.py
busline/event/message/number_message.py
busline/event/message/string_message.py
busline/local/__init__.py
busline/local/local_publisher.py
busline/local/local_subscriber.py
busline/local/eventbus/__init__.py
busline/local/eventbus/async_local_eventbus.py
busline/local/eventbus/eventbus.py
busline/local/eventbus/local_eventbus.py
busline/local/eventbus/wildcard_based_eventbus.py
busline/mqtt/__init__.py
busline/mqtt/mqtt_publisher.py
busline/mqtt/mqtt_subscriber.py
busline/utils/__init__.py
busline/utils/serde.py
busline/utils/singleton.py
busline/utils/task.py
busline-1.2.1.dist-info/licenses/LICENSE
busline-1.2.1.dist-info/METADATA
busline-1.2.1.dist-info/WHEEL
busline-1.2.1.dist-info/top_level.txt
busline-1.2.1.dist-info/RECORD
