Metadata-Version: 2.4
Name: busline
Version: 1.2.1
Summary: Agnostic Eventbus for Python
Author: Marco Picone
Author-email: Nicola Ricciardi <ricciardincl@gmail.com>
Project-URL: Homepage, https://github.com/orbitalis-framework/py-busline
Project-URL: Issues, https://github.com/orbitalis-framework/py-busline/issues
Classifier: Programming Language :: Python :: 3
Classifier: License :: OSI Approved :: MIT License
Classifier: Operating System :: OS Independent
Requires-Python: >=3.12
License-File: LICENSE
Requires-Dist: dataclasses_avroschema
Requires-Dist: aiomqtt
Dynamic: license-file
